capture_metric/__init__.py
capture_metric/capture.py
capture_metric/stop_words.py
capture_metric-0.1.13.dist-info/METADATA
capture_metric-0.1.13.dist-info/WHEEL
capture_metric-0.1.13.dist-info/top_level.txt
capture_metric-0.1.13.dist-info/RECORD
