Metadata-Version: 2.1
Name: capture_metric
Version: 0.1.13
Summary: A package for detail image caption evaluation.
Home-page: https://github.com/foundation-multimodal-models/CAPTURE
Author: Hongyuan Dong
Author-email: d_ousia@icloud.com
License: Apache-2.0
Requires-Dist: torch
Requires-Dist: transformers
Requires-Dist: tqdm
Requires-Dist: nltk
Requires-Dist: spacy
Requires-Dist: scipy
Requires-Dist: sentence-transformers
Requires-Dist: pandas
Requires-Dist: numpy
Requires-Dist: tabulate
Requires-Dist: FactualSceneGraph
